README.md
setup.py
fadetext/__init__.py
fadetext.egg-info/PKG-INFO
fadetext.egg-info/SOURCES.txt
fadetext.egg-info/dependency_links.txt
fadetext.egg-info/requires.txt
fadetext.egg-info/top_level.txt